graphstate_opt/ILP_SVMinor.py
graphstate_opt/ILP_VMinor.py
graphstate_opt/__init__.py
graphstate_opt/base_lc.py
graphstate_opt/edm_ilp.py
graphstate_opt/edm_sa.py
graphstate_opt/edm_sa_ilp.py
graphstate_opt/edm_test.py
graphstate_opt/wedm_ilp.py
graphstate_opt-1.1.4.dist-info/METADATA
graphstate_opt-1.1.4.dist-info/WHEEL
graphstate_opt-1.1.4.dist-info/licenses/LICENSE
graphstate_opt-1.1.4.dist-info/RECORD
