Metadata-Version: 2.4
Name: graphstate-opt
Version: 1.1.4
Summary: Package for graph-state-optimisation
Project-URL: Homepage, https://github.com/arr0w-hs/graph_state_optimization
Project-URL: Issues, https://github.com/arr0w-hs/graph_state_optimization/issues/
Project-URL: Releases, https://github.com/arr0w-hs/graph_state_optimization/releases
Author: Hemant Sharma, Kenneth Goodenough
License: MIT License
License-File: LICENSE
Classifier: Operating System :: OS Independent
Classifier: Programming Language :: Python :: 3
Classifier: Topic :: Software Development :: Libraries :: Python Modules
Requires-Python: >=3.9
Requires-Dist: cvxpy
Requires-Dist: matplotlib
Requires-Dist: numpy
Requires-Dist: pandas
Provides-Extra: mosek
Requires-Dist: mosek; extra == 'mosek'
